eclipse_pay/__init__.py
eclipse_pay-1.0.2.dist-info/LICENSE
eclipse_pay-1.0.2.dist-info/METADATA
eclipse_pay-1.0.2.dist-info/WHEEL
eclipse_pay-1.0.2.dist-info/top_level.txt
eclipse_pay-1.0.2.dist-info/RECORD
