Metadata-Version: 2.1
Name: eclipse-pay
Version: 1.0.2
Summary: Manage payments on scratch automatically.
Author: LIZARD_OFFICIAL
Author-email: <lizard.official.77@gmail.com>
Keywords: python,scratch,scratch.mit.edu,Blockbit,LRCOIN,BB,LRC,eclipseai
Classifier: Programming Language :: Python :: 3
License-File: LICENSE
Requires-Dist: scratchattach ==1.7.3
Requires-Dist: requests ==2.27.1
